cli_commands/LazyCommand.py
cli_commands/__init__.py
cli_commands/config.py
cli_commands/custom_commands.py
cli_commands/storage_commands.py
convert/__init__.py
convert/video_to_mp3.py
example/__init__.py
example/argparse.py
job_search/__init__.py
job_search/job_search_command.py
log/__init__.py
log/constants.py
log/estimate_task.py
log/log_setup.py
log/log_test.py
log/report_task.py
log/test_logger.py
log_chat/__init__.py
log_chat/chat_collector_command.py
log_task/__init__.py
log_task/constants.py
log_task/estimate_task.py
log_task/log_setup.py
log_task/log_test.py
log_task/report_task.py
log_vid/__init__.py
log_vid/video_data_command.py
scenes/__init__.py
scenes/model.py
scenes/read_scenes_command.py
scenes/write_scene_command.py
shared/__init__.py
shared/cli_command.py
shared/config.py
shared/constants.py
storage/__init__.py
storage/read.py
vid_to_mp3/__init__.py
vid_to_mp3/vid_to_mp3.py
vid_to_mp3/vid_to_mp3_command.py
atari_monk_cli_tool_commands-0.1.2.dist-info/METADATA
atari_monk_cli_tool_commands-0.1.2.dist-info/WHEEL
atari_monk_cli_tool_commands-0.1.2.dist-info/entry_points.txt
atari_monk_cli_tool_commands-0.1.2.dist-info/top_level.txt
atari_monk_cli_tool_commands-0.1.2.dist-info/RECORD
